sampleslicer/__init__.py
sampleslicer/cli.py
sampleslicer/sampleslicer.py
sampleslicer/template/sliceit.py
sampleslicer/template/slicetimestack.py
sampleslicer/tube/__init__.py
sampleslicer/tube/data.py
sampleslicer/tube/editor.py
sampleslicer/tube/extractor.py
sampleslicer-1.0.1.dist-info/LICENSE
sampleslicer-1.0.1.dist-info/METADATA
sampleslicer-1.0.1.dist-info/WHEEL
sampleslicer-1.0.1.dist-info/entry_points.txt
sampleslicer-1.0.1.dist-info/top_level.txt
sampleslicer-1.0.1.dist-info/RECORD
