Metadata-Version: 2.1
Name: sampleslicer
Version: 1.0.1
Summary: Graphically slice up 4-dimensional datasets using quaternions.
Home-page: https://doi.org/10.5281/zenodo.5523256
Author: John W
License: GPLv3
Platform: UNKNOWN
License-File: LICENSE
Requires-Dist: matplotlib
Requires-Dist: numpy
Requires-Dist: numpy-quaternion
Requires-Dist: scipy
Requires-Dist: imread (==0.7.4)
Requires-Dist: psutil (==5.8.0)
